{
  "image": {
    "width": 1920,
    "height": 1080,
    "depth": 3,
    "filename": "0209020.jpg",
    "class_map": {
      "0": "ordinary bee",
      "1": "pollen-bearing bee"
    }
  },
  "annotations": [
    {
      "class_id": 0,
      "bbox": [
        572.3333333333334,
        300.33333333333337,
        757.3333333333334,
        465.0
      ],
      "confidence": 0.46
    },
    {
      "class_id": 0,
      "bbox": [
        660.6666666666666,
        422.66666666666663,
        824.0,
        534.6666666666666
      ],
      "confidence": 0.45
    },
    {
      "class_id": 0,
      "bbox": [
        856.3333333333334,
        574.3333333333333,
        1041.3333333333333,
        765.3333333333333
      ],
      "confidence": 0.47
    },
    {
      "class_id": 0,
      "bbox": [
        574.6666666666666,
        577.3333333333333,
        708.0,
        753.0
      ],
      "confidence": 0.46
    },
    {
      "class_id": 0,
      "bbox": [
        648.3333333333334,
        647.0,
        779.0,
        828.0
      ],
      "confidence": 0.47
    },
    {
      "class_id": 0,
      "bbox": [
        838.6666666666666,
        803.0,
        948.0,
        861.3333333333334
      ],
      "confidence": 0.42
    }
  ]
}