{
  "image": {
    "width": 1920,
    "height": 1080,
    "depth": 3,
    "filename": "0721280.jpg",
    "class_map": {
      "0": "ordinary bee",
      "1": "pollen-bearing bee"
    }
  },
  "annotations": [
    {
      "class_id": 0,
      "bbox": [
        30.666666666666668,
        640.6666666666667,
        173.0,
        819.3333333333334
      ],
      "confidence": 0.43
    },
    {
      "class_id": 0,
      "bbox": [
        229.66666666666666,
        771.6666666666667,
        373.6666666666667,
        847.0
      ],
      "confidence": 0.42
    },
    {
      "class_id": 0,
      "bbox": [
        280.3333333333333,
        745.0,
        421.6666666666667,
        851.6666666666666
      ],
      "confidence": 0.42
    },
    {
      "class_id": 0,
      "bbox": [
        789.0,
        774.0,
        898.5,
        847.0
      ],
      "confidence": 0.25
    },
    {
      "class_id": 0,
      "bbox": [
        933.0,
        740.3333333333333,
        1078.6666666666667,
        847.3333333333333
      ],
      "confidence": 0.43
    },
    {
      "class_id": 0,
      "bbox": [
        1310.3333333333333,
        640.3333333333333,
        1427.6666666666667,
        801.3333333333333
      ],
      "confidence": 0.45
    },
    {
      "class_id": 0,
      "bbox": [
        1071.0,
        318.0,
        1274.6666666666667,
        483.33333333333337
      ],
      "confidence": 0.44
    },
    {
      "class_id": 0,
      "bbox": [
        806.0,
        581.0,
        944.6666666666666,
        723.6666666666667
      ],
      "confidence": 0.44
    },
    {
      "class_id": 0,
      "bbox": [
        704.3333333333334,
        437.0,
        932.0,
        593.6666666666667
      ],
      "confidence": 0.43
    }
  ]
}