{
  "image": {
    "width": 420,
    "height": 441,
    "depth": 3,
    "filename": "IMG_6961_0_1_0_1_0_1_0.jpg"
  },
  "raw annotations": [
    {
      "workerId": "public.us-east-1.A234WZ4KX8IW07",
      "lines": [
        [
          191,
          181,
          318,
          150
        ],
        [
          147,
          175,
          50,
          90
        ],
        [
          198,
          225,
          141,
          339
        ],
        [
          76,
          327,
          126,
          227
        ],
        [
          90,
          191,
          0,
          206
        ],
        [
          16,
          335,
          1,
          244
        ],
        [
          230,
          269,
          329,
          230
        ],
        [
          169,
          135,
          126,
          39
        ],
        [
          141,
          268,
          178,
          165
        ],
        [
          58,
          357,
          154,
          424
        ],
        [
          153,
          375,
          220,
          289
        ],
        [
          364,
          370,
          297,
          282
        ],
        [
          404,
          246,
          352,
          228
        ],
        [
          224,
          341,
          237,
          415
        ],
        [
          158,
          374,
          200,
          432
        ],
        [
          415,
          218,
          418,
          313
        ]
      ]
    },
    {
      "workerId": "public.us-east-1.ATTBQJ167LYH5",
      "lines": [
        [
          143,
          172,
          53,
          95
        ],
        [
          7,
          2,
          19,
          76
        ],
        [
          126,
          24,
          141,
          112
        ],
        [
          200,
          174,
          312,
          153
        ],
        [
          393,
          269,
          348,
          215
        ],
        [
          226,
          262,
          336,
          253
        ],
        [
          355,
          358,
          303,
          293
        ],
        [
          93,
          193,
          0,
          205
        ],
        [
          65,
          324,
          124,
          234
        ],
        [
          172,
          176,
          143,
          253
        ],
        [
          138,
          319,
          198,
          224
        ],
        [
          68,
          356,
          148,
          421
        ],
        [
          150,
          361,
          190,
          427
        ],
        [
          230,
          345,
          228,
          413
        ],
        [
          165,
          350,
          212,
          300
        ],
        [
          413,
          380,
          391,
          380
        ],
        [
          19,
          329,
          2,
          243
        ]
      ]
    },
    {
      "workerId": "public.us-east-1.A2JBJFPFG38X9C",
      "lines": [
        [
          359,
          374,
          287,
          284
        ],
        [
          222,
          263,
          325,
          219
        ],
        [
          405,
          307,
          343,
          206
        ],
        [
          186,
          187,
          308,
          147
        ],
        [
          54,
          353,
          151,
          418
        ],
        [
          147,
          336,
          170,
          397
        ],
        [
          231,
          327,
          207,
          397
        ],
        [
          220,
          286,
          174,
          364
        ],
        [
          126,
          332,
          207,
          227
        ],
        [
          59,
          323,
          126,
          225
        ],
        [
          133,
          286,
          174,
          172
        ],
        [
          143,
          173,
          56,
          104
        ],
        [
          10,
          339,
          0,
          242
        ],
        [
          32,
          155,
          0,
          121
        ],
        [
          0,
          203,
          100,
          188
        ]
      ]
    }
  ],
  "consolidated annotations": [
    {
      "line": [
        143.0,
        173.0,
        53.0,
        95.0
      ],
      "num_annotator": 3,
      "num_flip": 0
    },
    {
      "line": [
        126.0,
        31.5,
        155.0,
        123.5
      ],
      "num_annotator": 2,
      "num_flip": 1
    },
    {
      "line": [
        191.0,
        181.0,
        312.0,
        150.0
      ],
      "num_annotator": 3,
      "num_flip": 0
    },
    {
      "line": [
        404.0,
        269.0,
        348.0,
        215.0
      ],
      "num_annotator": 3,
      "num_flip": 0
    },
    {
      "line": [
        226.0,
        263.0,
        329.0,
        230.0
      ],
      "num_annotator": 3,
      "num_flip": 0
    },
    {
      "line": [
        359.0,
        370.0,
        297.0,
        284.0
      ],
      "num_annotator": 3,
      "num_flip": 0
    },
    {
      "line": [
        93.0,
        191.0,
        0.0,
        205.0
      ],
      "num_annotator": 3,
      "num_flip": 1
    },
    {
      "line": [
        65.0,
        324.0,
        126.0,
        227.0
      ],
      "num_annotator": 3,
      "num_flip": 0
    },
    {
      "line": [
        141.0,
        268.0,
        174.0,
        172.0
      ],
      "num_annotator": 3,
      "num_flip": 1
    },
    {
      "line": [
        138.0,
        332.0,
        198.0,
        225.0
      ],
      "num_annotator": 3,
      "num_flip": 1
    },
    {
      "line": [
        58.0,
        356.0,
        151.0,
        421.0
      ],
      "num_annotator": 3,
      "num_flip": 0
    },
    {
      "line": [
        154.0,
        367.5,
        195.0,
        429.5
      ],
      "num_annotator": 2,
      "num_flip": 0
    },
    {
      "line": [
        230.0,
        341.0,
        228.0,
        413.0
      ],
      "num_annotator": 3,
      "num_flip": 0
    },
    {
      "line": [
        165.0,
        364.0,
        220.0,
        289.0
      ],
      "num_annotator": 3,
      "num_flip": 1
    },
    {
      "line": [
        16.0,
        335.0,
        1.0,
        243.0
      ],
      "num_annotator": 3,
      "num_flip": 0
    }
  ]
}