{
  "image": {
    "width": 420,
    "height": 423,
    "depth": 3,
    "filename": "IMG_6092_0_1_1_0_0_1_0.jpg"
  },
  "raw annotations": [
    {
      "workerId": "public.us-east-1.ANHH3N0535YSN",
      "lines": [
        [
          328,
          25,
          327,
          158
        ],
        [
          269,
          85,
          307,
          228
        ],
        [
          259,
          195,
          152,
          203
        ],
        [
          117,
          32,
          197,
          143
        ],
        [
          183,
          1,
          223,
          118
        ],
        [
          102,
          16,
          14,
          119
        ],
        [
          84,
          327,
          51,
          203
        ],
        [
          196,
          232,
          167,
          351
        ],
        [
          69,
          416,
          181,
          379
        ],
        [
          252,
          326,
          390,
          326
        ],
        [
          291,
          380,
          408,
          363
        ],
        [
          38,
          393,
          7,
          389
        ],
        [
          5,
          185,
          126,
          149
        ]
      ]
    },
    {
      "workerId": "public.us-east-1.A234WZ4KX8IW07",
      "lines": [
        [
          329,
          37,
          325,
          162
        ],
        [
          182,
          6,
          221,
          120
        ],
        [
          120,
          42,
          204,
          142
        ],
        [
          64,
          219,
          86,
          323
        ],
        [
          249,
          192,
          147,
          203
        ],
        [
          376,
          319,
          266,
          329
        ],
        [
          11,
          119,
          97,
          18
        ],
        [
          3,
          178,
          120,
          147
        ],
        [
          241,
          97,
          295,
          14
        ],
        [
          168,
          346,
          206,
          241
        ],
        [
          400,
          364,
          297,
          377
        ],
        [
          67,
          419,
          183,
          384
        ],
        [
          25,
          392,
          0,
          397
        ]
      ]
    },
    {
      "workerId": "public.us-east-1.AH31KYC8IKTZZ",
      "lines": [
        [
          329,
          29,
          334,
          135
        ],
        [
          276,
          123,
          302,
          210
        ],
        [
          247,
          194,
          146,
          208
        ],
        [
          168,
          340,
          195,
          248
        ],
        [
          52,
          229,
          82,
          317
        ],
        [
          8,
          177,
          113,
          153
        ],
        [
          120,
          45,
          190,
          132
        ],
        [
          186,
          4,
          217,
          112
        ],
        [
          245,
          88,
          276,
          14
        ],
        [
          93,
          18,
          13,
          112
        ],
        [
          273,
          323,
          360,
          322
        ],
        [
          391,
          359,
          312,
          375
        ],
        [
          68,
          412,
          177,
          385
        ],
        [
          370,
          395,
          357,
          417
        ],
        [
          407,
          390,
          410,
          415
        ]
      ]
    }
  ],
  "consolidated annotations": [
    {
      "line": [
        329.0,
        29.0,
        327.0,
        158.0
      ],
      "num_annotator": 3,
      "num_flip": 0
    },
    {
      "line": [
        272.5,
        104.0,
        304.5,
        219.0
      ],
      "num_annotator": 2,
      "num_flip": 0
    },
    {
      "line": [
        249.0,
        194.0,
        147.0,
        203.0
      ],
      "num_annotator": 3,
      "num_flip": 0
    },
    {
      "line": [
        168.0,
        346.0,
        196.0,
        241.0
      ],
      "num_annotator": 3,
      "num_flip": 1
    },
    {
      "line": [
        52.0,
        219.0,
        84.0,
        323.0
      ],
      "num_annotator": 3,
      "num_flip": 1
    },
    {
      "line": [
        5.0,
        178.0,
        120.0,
        149.0
      ],
      "num_annotator": 3,
      "num_flip": 0
    },
    {
      "line": [
        120.0,
        42.0,
        197.0,
        142.0
      ],
      "num_annotator": 3,
      "num_flip": 0
    },
    {
      "line": [
        183.0,
        4.0,
        221.0,
        118.0
      ],
      "num_annotator": 3,
      "num_flip": 0
    },
    {
      "line": [
        243.0,
        92.5,
        285.5,
        14.0
      ],
      "num_annotator": 2,
      "num_flip": 0
    },
    {
      "line": [
        97.0,
        18.0,
        13.0,
        119.0
      ],
      "num_annotator": 3,
      "num_flip": 1
    },
    {
      "line": [
        266.0,
        326.0,
        376.0,
        322.0
      ],
      "num_annotator": 3,
      "num_flip": 1
    },
    {
      "line": [
        400.0,
        363.0,
        297.0,
        377.0
      ],
      "num_annotator": 3,
      "num_flip": 1
    },
    {
      "line": [
        68.0,
        416.0,
        181.0,
        384.0
      ],
      "num_annotator": 3,
      "num_flip": 0
    },
    {
      "line": [
        31.5,
        392.5,
        3.5,
        393.0
      ],
      "num_annotator": 2,
      "num_flip": 0
    }
  ]
}