{
  "image": {
    "width": 421,
    "height": 441,
    "depth": 3,
    "filename": "IMG_6380_1_1_1_0_0_1_1.jpg"
  },
  "raw annotations": [
    {
      "workerId": "public.us-east-1.AB3EII39KUEPS",
      "lines": [
        [
          113,
          28,
          105,
          151
        ],
        [
          233,
          53,
          164,
          148
        ],
        [
          249,
          105,
          233,
          216
        ],
        [
          198,
          173,
          123,
          264
        ],
        [
          1,
          225,
          65,
          209
        ],
        [
          7,
          33,
          71,
          14
        ],
        [
          312,
          166,
          349,
          260
        ],
        [
          339,
          129,
          382,
          218
        ],
        [
          335,
          88,
          290,
          160
        ],
        [
          279,
          222,
          245,
          335
        ],
        [
          178,
          264,
          198,
          373
        ],
        [
          110,
          330,
          172,
          427
        ],
        [
          333,
          353,
          239,
          404
        ],
        [
          413,
          229,
          372,
          248
        ],
        [
          349,
          298,
          268,
          337
        ],
        [
          390,
          341,
          389,
          436
        ],
        [
          221,
          19,
          110,
          11
        ],
        [
          294,
          9,
          340,
          80
        ],
        [
          411,
          21,
          295,
          58
        ],
        [
          421,
          83,
          349,
          90
        ]
      ]
    },
    {
      "workerId": "public.us-east-1.AH31KYC8IKTZZ",
      "lines": [
        [
          132,
          257,
          191,
          188
        ],
        [
          256,
          111,
          221,
          201
        ],
        [
          182,
          260,
          196,
          369
        ],
        [
          100,
          328,
          155,
          405
        ],
        [
          278,
          229,
          253,
          327
        ],
        [
          311,
          171,
          342,
          252
        ],
        [
          350,
          126,
          368,
          207
        ],
        [
          313,
          95,
          285,
          158
        ],
        [
          224,
          57,
          170,
          138
        ],
        [
          111,
          38,
          106,
          144
        ],
        [
          48,
          207,
          8,
          217
        ],
        [
          3,
          279,
          7,
          369
        ],
        [
          46,
          431,
          87,
          423
        ],
        [
          229,
          402,
          339,
          361
        ],
        [
          386,
          340,
          391,
          427
        ],
        [
          200,
          407,
          199,
          440
        ],
        [
          372,
          248,
          418,
          234
        ],
        [
          393,
          125,
          414,
          144
        ],
        [
          295,
          6,
          333,
          75
        ],
        [
          109,
          8,
          202,
          18
        ],
        [
          53,
          14,
          1,
          40
        ],
        [
          28,
          77,
          6,
          92
        ]
      ]
    },
    {
      "workerId": "public.us-east-1.A1V8ZC4O3AISA5",
      "lines": [
        [
          103,
          31,
          98,
          158
        ],
        [
          219,
          22,
          96,
          10
        ],
        [
          60,
          8,
          12,
          33
        ],
        [
          30,
          75,
          0,
          101
        ],
        [
          59,
          210,
          5,
          225
        ],
        [
          131,
          264,
          201,
          163
        ],
        [
          168,
          253,
          194,
          343
        ],
        [
          279,
          223,
          243,
          336
        ],
        [
          293,
          306,
          390,
          305
        ],
        [
          312,
          163,
          343,
          270
        ],
        [
          348,
          120,
          368,
          226
        ],
        [
          366,
          253,
          420,
          227
        ],
        [
          384,
          132,
          421,
          157
        ],
        [
          335,
          96,
          421,
          69
        ],
        [
          278,
          3,
          332,
          78
        ],
        [
          267,
          165,
          320,
          86
        ],
        [
          258,
          107,
          221,
          221
        ],
        [
          231,
          45,
          156,
          143
        ],
        [
          95,
          324,
          164,
          432
        ],
        [
          3,
          275,
          4,
          384
        ],
        [
          202,
          403,
          202,
          441
        ],
        [
          117,
          409,
          41,
          435
        ],
        [
          337,
          352,
          224,
          405
        ],
        [
          393,
          340,
          384,
          437
        ]
      ]
    }
  ],
  "consolidated annotations": [
    {
      "line": [
        111.0,
        31.0,
        105.0,
        151.0
      ],
      "num_annotator": 3,
      "num_flip": 0
    },
    {
      "line": [
        219.0,
        19.0,
        109.0,
        10.0
      ],
      "num_annotator": 3,
      "num_flip": 1
    },
    {
      "line": [
        60.0,
        14.0,
        7.0,
        33.0
      ],
      "num_annotator": 3,
      "num_flip": 1
    },
    {
      "line": [
        29.0,
        76.0,
        3.0,
        96.5
      ],
      "num_annotator": 2,
      "num_flip": 0
    },
    {
      "line": [
        59.0,
        209.0,
        5.0,
        225.0
      ],
      "num_annotator": 3,
      "num_flip": 1
    },
    {
      "line": [
        131.0,
        264.0,
        198.0,
        173.0
      ],
      "num_annotator": 3,
      "num_flip": 1
    },
    {
      "line": [
        178.0,
        260.0,
        196.0,
        369.0
      ],
      "num_annotator": 3,
      "num_flip": 0
    },
    {
      "line": [
        279.0,
        223.0,
        245.0,
        335.0
      ],
      "num_annotator": 3,
      "num_flip": 0
    },
    {
      "line": [
        312.0,
        166.0,
        343.0,
        260.0
      ],
      "num_annotator": 3,
      "num_flip": 0
    },
    {
      "line": [
        348.0,
        126.0,
        368.0,
        218.0
      ],
      "num_annotator": 3,
      "num_flip": 0
    },
    {
      "line": [
        372.0,
        248.0,
        418.0,
        229.0
      ],
      "num_annotator": 3,
      "num_flip": 1
    },
    {
      "line": [
        388.5,
        128.5,
        417.5,
        150.5
      ],
      "num_annotator": 2,
      "num_flip": 0
    },
    {
      "line": [
        342.0,
        93.0,
        421.0,
        76.0
      ],
      "num_annotator": 2,
      "num_flip": 1
    },
    {
      "line": [
        294.0,
        6.0,
        333.0,
        78.0
      ],
      "num_annotator": 3,
      "num_flip": 0
    },
    {
      "line": [
        320.0,
        88.0,
        285.0,
        160.0
      ],
      "num_annotator": 3,
      "num_flip": 1
    },
    {
      "line": [
        256.0,
        107.0,
        221.0,
        216.0
      ],
      "num_annotator": 3,
      "num_flip": 0
    },
    {
      "line": [
        231.0,
        53.0,
        164.0,
        143.0
      ],
      "num_annotator": 3,
      "num_flip": 0
    },
    {
      "line": [
        100.0,
        328.0,
        164.0,
        427.0
      ],
      "num_annotator": 3,
      "num_flip": 0
    },
    {
      "line": [
        3.0,
        277.0,
        5.5,
        376.5
      ],
      "num_annotator": 2,
      "num_flip": 0
    },
    {
      "line": [
        201.0,
        405.0,
        200.5,
        440.5
      ],
      "num_annotator": 2,
      "num_flip": 0
    },
    {
      "line": [
        102.0,
        416.0,
        43.5,
        433.0
      ],
      "num_annotator": 2,
      "num_flip": 1
    },
    {
      "line": [
        337.0,
        353.0,
        229.0,
        404.0
      ],
      "num_annotator": 3,
      "num_flip": 1
    },
    {
      "line": [
        390.0,
        340.0,
        389.0,
        436.0
      ],
      "num_annotator": 3,
      "num_flip": 0
    }
  ]
}