{
  "image": {
    "width": 421,
    "height": 441,
    "depth": 3,
    "filename": "IMG_6406_0_1_1_1_1_1_1.jpg"
  },
  "raw annotations": [
    {
      "workerId": "public.us-east-1.A1YMJ1WD1OK02A",
      "lines": [
        [
          391,
          206,
          289,
          178
        ],
        [
          268,
          234,
          200,
          189
        ],
        [
          139,
          172,
          90,
          291
        ],
        [
          111,
          186,
          16,
          175
        ],
        [
          94,
          0,
          30,
          106
        ],
        [
          56,
          147,
          151,
          95
        ],
        [
          131,
          18,
          111,
          80
        ],
        [
          283,
          19,
          245,
          130
        ],
        [
          324,
          145,
          215,
          172
        ],
        [
          215,
          69,
          150,
          178
        ],
        [
          340,
          104,
          420,
          158
        ],
        [
          332,
          2,
          376,
          97
        ],
        [
          225,
          1,
          233,
          93
        ],
        [
          21,
          0,
          37,
          52
        ],
        [
          160,
          0,
          157,
          0
        ],
        [
          156,
          1,
          175,
          76
        ],
        [
          288,
          98,
          373,
          165
        ]
      ]
    },
    {
      "workerId": "public.us-east-1.A3AFUDAVEUV2GG",
      "lines": [
        [
          124,
          191,
          93,
          293
        ],
        [
          24,
          162,
          104,
          187
        ],
        [
          199,
          196,
          254,
          220
        ],
        [
          139,
          167,
          195,
          84
        ],
        [
          131,
          10,
          129,
          48
        ],
        [
          35,
          124,
          166,
          123
        ],
        [
          263,
          79,
          300,
          26
        ],
        [
          315,
          176,
          376,
          203
        ],
        [
          314,
          154,
          254,
          162
        ],
        [
          311,
          120,
          355,
          159
        ],
        [
          372,
          117,
          419,
          153
        ],
        [
          336,
          8,
          353,
          108
        ],
        [
          226,
          7,
          234,
          92
        ],
        [
          102,
          6,
          49,
          86
        ],
        [
          376,
          6,
          393,
          79
        ],
        [
          72,
          381,
          7,
          423
        ],
        [
          96,
          419,
          69,
          429
        ]
      ]
    },
    {
      "workerId": "public.us-east-1.A46QYH5KWB976",
      "lines": [
        [
          79,
          7,
          46,
          77
        ],
        [
          129,
          91,
          55,
          113
        ],
        [
          208,
          74,
          153,
          152
        ],
        [
          279,
          30,
          239,
          130
        ],
        [
          296,
          146,
          223,
          173
        ],
        [
          310,
          168,
          365,
          204
        ],
        [
          194,
          193,
          264,
          245
        ],
        [
          137,
          182,
          106,
          277
        ],
        [
          16,
          180,
          95,
          195
        ],
        [
          226,
          11,
          230,
          91
        ],
        [
          339,
          18,
          367,
          91
        ],
        [
          298,
          105,
          369,
          153
        ],
        [
          355,
          104,
          415,
          153
        ],
        [
          164,
          5,
          188,
          75
        ]
      ]
    }
  ],
  "consolidated annotations": [
    {
      "line": [
        137.0,
        182.0,
        93.0,
        291.0
      ],
      "num_annotator": 3,
      "num_flip": 0
    },
    {
      "line": [
        16.0,
        175.0,
        104.0,
        187.0
      ],
      "num_annotator": 3,
      "num_flip": 1
    },
    {
      "line": [
        199.0,
        193.0,
        264.0,
        234.0
      ],
      "num_annotator": 3,
      "num_flip": 1
    },
    {
      "line": [
        208.0,
        74.0,
        150.0,
        167.0
      ],
      "num_annotator": 3,
      "num_flip": 1
    },
    {
      "line": [
        131.0,
        14.0,
        120.0,
        64.0
      ],
      "num_annotator": 2,
      "num_flip": 0
    },
    {
      "line": [
        55.0,
        124.0,
        151.0,
        95.0
      ],
      "num_annotator": 3,
      "num_flip": 1
    },
    {
      "line": [
        254.0,
        104.5,
        291.5,
        22.5
      ],
      "num_annotator": 2,
      "num_flip": 1
    },
    {
      "line": [
        310.0,
        176.0,
        376.0,
        204.0
      ],
      "num_annotator": 3,
      "num_flip": 1
    },
    {
      "line": [
        314.0,
        146.0,
        223.0,
        172.0
      ],
      "num_annotator": 3,
      "num_flip": 0
    },
    {
      "line": [
        298.0,
        105.0,
        369.0,
        159.0
      ],
      "num_annotator": 3,
      "num_flip": 0
    },
    {
      "line": [
        355.0,
        104.0,
        419.0,
        153.0
      ],
      "num_annotator": 3,
      "num_flip": 0
    },
    {
      "line": [
        336.0,
        8.0,
        367.0,
        97.0
      ],
      "num_annotator": 3,
      "num_flip": 0
    },
    {
      "line": [
        226.0,
        7.0,
        233.0,
        92.0
      ],
      "num_annotator": 3,
      "num_flip": 0
    },
    {
      "line": [
        94.0,
        6.0,
        46.0,
        86.0
      ],
      "num_annotator": 3,
      "num_flip": 0
    },
    {
      "line": [
        160.0,
        3.0,
        181.5,
        75.5
      ],
      "num_annotator": 2,
      "num_flip": 0
    }
  ]
}