{
  "image": {
    "width": 408,
    "height": 424,
    "depth": 3,
    "filename": "IMG_6970_1_1_1_1_0_1_0.jpg"
  },
  "raw annotations": [
    {
      "workerId": "public.us-east-1.AT3HPICJ6SAOA",
      "lines": [
        [
          179,
          128,
          216,
          58
        ],
        [
          265,
          153,
          332,
          142
        ],
        [
          5,
          107,
          108,
          133
        ],
        [
          8,
          25,
          75,
          91
        ],
        [
          7,
          205,
          92,
          196
        ],
        [
          71,
          309,
          160,
          292
        ],
        [
          172,
          243,
          241,
          301
        ],
        [
          257,
          285,
          356,
          229
        ],
        [
          209,
          200,
          290,
          199
        ],
        [
          403,
          228,
          358,
          336
        ],
        [
          336,
          265,
          287,
          350
        ],
        [
          78,
          364,
          180,
          355
        ],
        [
          113,
          89,
          195,
          41
        ],
        [
          393,
          63,
          366,
          10
        ],
        [
          228,
          24,
          257,
          50
        ],
        [
          97,
          39,
          183,
          20
        ]
      ]
    },
    {
      "workerId": "public.us-east-1.A2MFLFNXFI4437",
      "lines": [
        [
          60,
          62,
          50,
          90
        ],
        [
          86,
          74,
          128,
          57
        ],
        [
          70,
          125,
          133,
          107
        ],
        [
          118,
          136,
          70,
          202
        ],
        [
          30,
          239,
          41,
          232
        ],
        [
          57,
          285,
          153,
          260
        ],
        [
          70,
          369,
          141,
          346
        ],
        [
          199,
          314,
          294,
          290
        ],
        [
          299,
          239,
          314,
          231
        ],
        [
          237,
          263,
          271,
          136
        ],
        [
          332,
          138,
          332,
          93
        ],
        [
          373,
          203,
          369,
          272
        ],
        [
          273,
          106,
          318,
          42
        ],
        [
          179,
          26,
          208,
          114
        ],
        [
          237,
          81,
          265,
          26
        ]
      ]
    },
    {
      "workerId": "public.us-east-1.A3AFUDAVEUV2GG",
      "lines": [
        [
          110,
          122,
          0,
          127
        ],
        [
          67,
          186,
          58,
          186
        ],
        [
          84,
          184,
          0,
          187
        ],
        [
          8,
          197,
          137,
          281
        ],
        [
          27,
          289,
          13,
          322
        ],
        [
          87,
          337,
          183,
          346
        ],
        [
          154,
          239,
          251,
          294
        ],
        [
          166,
          164,
          260,
          120
        ],
        [
          226,
          211,
          288,
          191
        ],
        [
          267,
          154,
          330,
          154
        ],
        [
          120,
          90,
          184,
          36
        ],
        [
          325,
          226,
          245,
          274
        ],
        [
          350,
          256,
          301,
          353
        ],
        [
          385,
          259,
          375,
          326
        ],
        [
          366,
          162,
          404,
          94
        ],
        [
          225,
          43,
          199,
          122
        ],
        [
          356,
          64,
          259,
          13
        ]
      ]
    }
  ],
  "consolidated annotations": [
    {
      "line": [
        109.0,
        127.5,
        2.5,
        117.0
      ],
      "num_annotator": 2,
      "num_flip": 1
    },
    {
      "line": [
        79.5,
        191.0,
        32.5,
        195.5
      ],
      "num_annotator": 2,
      "num_flip": 1
    },
    {
      "line": [
        82.5,
        350.5,
        181.5,
        350.5
      ],
      "num_annotator": 2,
      "num_flip": 0
    },
    {
      "line": [
        163.0,
        241.0,
        246.0,
        297.5
      ],
      "num_annotator": 2,
      "num_flip": 0
    },
    {
      "line": [
        226.0,
        211.0,
        288.0,
        191.0
      ],
      "num_annotator": 3,
      "num_flip": 0
    },
    {
      "line": [
        266.0,
        153.5,
        331.0,
        148.0
      ],
      "num_annotator": 2,
      "num_flip": 0
    },
    {
      "line": [
        116.5,
        89.5,
        189.5,
        38.5
      ],
      "num_annotator": 2,
      "num_flip": 0
    },
    {
      "line": [
        257.0,
        274.0,
        325.0,
        229.0
      ],
      "num_annotator": 3,
      "num_flip": 1
    },
    {
      "line": [
        343.0,
        260.5,
        294.0,
        351.5
      ],
      "num_annotator": 2,
      "num_flip": 0
    },
    {
      "line": [
        394.0,
        243.5,
        366.5,
        331.0
      ],
      "num_annotator": 2,
      "num_flip": 0
    },
    {
      "line": [
        216.0,
        43.0,
        199.0,
        122.0
      ],
      "num_annotator": 3,
      "num_flip": 1
    },
    {
      "line": [
        34.0,
        43.5,
        62.5,
        90.5
      ],
      "num_annotator": 2,
      "num_flip": 0
    },
    {
      "line": [
        246.5,
        25.0,
        247.0,
        65.5
      ],
      "num_annotator": 2,
      "num_flip": 1
    }
  ]
}